MANIFEST.in
README.md
setup.cfg
setup.py
version.py
limix_sphinx_theme/__init__.py
limix_sphinx_theme/_testit.py
limix_sphinx_theme.egg-info/PKG-INFO
limix_sphinx_theme.egg-info/SOURCES.txt
limix_sphinx_theme.egg-info/dependency_links.txt
limix_sphinx_theme.egg-info/entry_points.txt
limix_sphinx_theme.egg-info/not-zip-safe
limix_sphinx_theme.egg-info/requires.txt
limix_sphinx_theme.egg-info/top_level.txt
limix_sphinx_theme/bootstrap-limix/layout.html
limix_sphinx_theme/bootstrap-limix/theme.conf
limix_sphinx_theme/bootstrap-limix/static/bootstrap-limix.css
limix_sphinx_theme/bootstrap-limix/static/copybutton.js
limix_sphinx_theme/test/__init__.py
limix_sphinx_theme/test/test_api.py