Metadata-Version: 2.1
Name: limix-sphinx-theme
Version: 0.0.2
Summary: Limix bootstrap theme.
Home-page: https://github.com/limix/limix-sphinx-theme
Author: D. Horta
Author-email: horta@ebi.ac.uk
Maintainer: Danilo Horta
Maintainer-email: horta@ebi.ac.uk
License: MIT
Download-URL: https://github.com/limix/limix-sphinx-theme
Keywords: limix,theme
Platform: Windows
Platform: MacOS
Platform: Linux
Classifier: Development Status :: 5 - Production/Stable
Classifier: Environment :: Console
Classifier: Intended Audience :: Developers
Classifier: License :: OSI Approved :: MIT License
Classifier: Operating System :: OS Independent
Classifier: Programming Language :: Python
